nonebot_plugin_filehost-1.1.0.dist-info/METADATA
nonebot_plugin_filehost-1.1.0.dist-info/WHEEL
nonebot_plugin_filehost-1.1.0.dist-info/licenses/LICENSE
nonebot_plugin_filehost/__init__.py
nonebot_plugin_filehost/models.py
nonebot_plugin_filehost/plugin_config.py
nonebot_plugin_filehost-1.1.0.dist-info/RECORD
