Metadata-Version: 2.1
Name: nonebot-plugin-filehost
Version: 1.1.0
Summary: Effortless static file hosting plugin for NoneBot2.
Author-Email: Mix <32300164+mnixry@users.noreply.github.com>
License: MIT
Requires-Python: >=3.8
Requires-Dist: nonebot2[fastapi]>=2.2.0
Requires-Dist: anyio>=3
